firebase_drf_auth/__init__.py
firebase_drf_auth/auth.py
firebase_drf_auth/migrations/0001_initial.py
firebase_drf_auth/migrations/__init__.py
firebase_drf_auth/models.py
firebase_drf_auth-0.1.5.dist-info/METADATA
firebase_drf_auth-0.1.5.dist-info/WHEEL
firebase_drf_auth-0.1.5.dist-info/RECORD
