Metadata-Version: 2.1
Name: firebase-drf-auth
Version: 0.1.5
Summary: 
Author: sazonov-src
Author-email: sazonov89vit@gmail.com
Requires-Python: >=3.10,<4.0
Classifier: Programming Language :: Python :: 3
Classifier: Programming Language :: Python :: 3.10
Classifier: Programming Language :: Python :: 3.11
Requires-Dist: djangorestframework (>=3.14.0,<4.0.0)
Requires-Dist: firebase-admin (>=6.4.0,<7.0.0)
